jhub_apps/__about__.py
jhub_apps/__init__.py
jhub_apps/config_utils.py
jhub_apps/configuration.py
jhub_apps/main.py
jhub_apps/version.py
jhub_apps/examples/__init__.py
jhub_apps/examples/bokeh_basic.py
jhub_apps/examples/gradio_basic.py
jhub_apps/examples/panel_basic.py
jhub_apps/examples/plotlydash_app.py
jhub_apps/examples/streamlit_app.py
jhub_apps/examples/voila_basic.ipynb
jhub_apps/hub_client/__init__.py
jhub_apps/hub_client/hub_client.py
jhub_apps/hub_client/utils.py
jhub_apps/service/__init__.py
jhub_apps/service/app.py
jhub_apps/service/app_from_git.py
jhub_apps/service/auth.py
jhub_apps/service/client.py
jhub_apps/service/japps_routes.py
jhub_apps/service/logging_utils.py
jhub_apps/service/middlewares.py
jhub_apps/service/models.py
jhub_apps/service/routes.py
jhub_apps/service/security.py
jhub_apps/service/utils.py
jhub_apps/spawner/__init__.py
jhub_apps/spawner/command.py
jhub_apps/spawner/spawner_creation.py
jhub_apps/spawner/types.py
jhub_apps/spawner/utils.py
jhub_apps/static/favicon.ico
jhub_apps/static/css/index.css
jhub_apps/static/img/Nebari-Logo-Horizontal-Lockup-Black-text.svg
jhub_apps/static/img/Nebari-Logo-Horizontal-Lockup-White-text.svg
jhub_apps/static/img/Nebari-logo-square.svg
jhub_apps/static/img/logos/bokeh.png
jhub_apps/static/img/logos/conda-store.png
jhub_apps/static/img/logos/custom.png
jhub_apps/static/img/logos/gradio.png
jhub_apps/static/img/logos/jupyter.png
jhub_apps/static/img/logos/panel.png
jhub_apps/static/img/logos/plotly-dash.png
jhub_apps/static/img/logos/streamlit.png
jhub_apps/static/img/logos/voila.png
jhub_apps/static/img/logos/vscode.png
jhub_apps/static/js/index.js
jhub_apps/tasks/commands/initialize_startup_apps.py
jhub_apps/templates/404.html
jhub_apps/templates/home.html
jhub_apps/templates/japps_custom.html
jhub_apps/templates/japps_page.html
jhub_apps/templates/launcher_base.html
jhub_apps/templates/login.html
jhub_apps/templates/not_running.html
jhub_apps/templates/oauth.html
jhub_apps/templates/page.html
jhub_apps-2025.8.1.dist-info/METADATA
jhub_apps-2025.8.1.dist-info/WHEEL
jhub_apps-2025.8.1.dist-info/entry_points.txt
jhub_apps-2025.8.1.dist-info/licenses/LICENSE
jhub_apps-2025.8.1.dist-info/RECORD
