Metadata-Version: 2.4
Name: jhub-apps
Version: 2025.8.1
Summary: JupyterHub Apps
License-Expression: MIT
License-File: LICENSE
Requires-Python: >=3.8
Requires-Dist: bokeh
Requires-Dist: bokeh-root-cmd
Requires-Dist: cachetools
Requires-Dist: conda-project==0.4.2
Requires-Dist: fastapi
Requires-Dist: gitpython
Requires-Dist: hatch
Requires-Dist: hatchling
Requires-Dist: jhsingle-native-proxy==0.8.3
Requires-Dist: jupyter
Requires-Dist: jupyterhub>4
Requires-Dist: panel
Requires-Dist: plotlydash-tornado-cmd
Requires-Dist: pyjwt<2.10.0
Requires-Dist: python-multipart
Requires-Dist: python-slugify
Requires-Dist: requests
Requires-Dist: structlog
Requires-Dist: traitlets
Requires-Dist: uvicorn
Provides-Extra: dev
Requires-Dist: dash; extra == 'dev'
Requires-Dist: gradio; extra == 'dev'
Requires-Dist: playwright; extra == 'dev'
Requires-Dist: pre-commit; extra == 'dev'
Requires-Dist: pytest; extra == 'dev'
Requires-Dist: pytest-playwright; extra == 'dev'
Requires-Dist: ruff; extra == 'dev'
Requires-Dist: streamlit; extra == 'dev'
Requires-Dist: voila; extra == 'dev'
